hermes/__init__.py
hermes/conftest.py
hermes/cli/__init__.py
hermes/cli/database.py
hermes/cli/forecast.py
hermes/cli/forecastseries.py
hermes/cli/injectionplan.py
hermes/cli/model.py
hermes/cli/project.py
hermes/cli/schedule.py
hermes/cli/utils.py
hermes/config/__init__.py
hermes/config/blocks.py
hermes/config/config.py
hermes/config/gunicorn.py
hermes/config/tests/test_blocks.py
hermes/datamodel/__init__.py
hermes/datamodel/base.py
hermes/datamodel/data_tables.py
hermes/datamodel/project_tables.py
hermes/datamodel/result_tables.py
hermes/datamodel/alembic/README.md
hermes/datamodel/alembic/__init__.py
hermes/datamodel/alembic/alembic.ini
hermes/datamodel/alembic/env.py
hermes/datamodel/alembic/functions.py
hermes/datamodel/alembic/init-prefect-db.sql
hermes/datamodel/alembic/postgresql.conf
hermes/datamodel/alembic/script.py.mako
hermes/datamodel/alembic/utils.py
hermes/datamodel/alembic/versions/0c7b5c0d13d9_create_schema_branch.py
hermes/datamodel/alembic/versions/3c9be082f685_add_modelrun_oid_to_grparameters.py
hermes/datamodel/alembic/versions/c164eff8a1f3_add_indexes_for_natural_forecasts.py
hermes/datamodel/alembic/versions/cd951716a1c8_add_indexes_for_modelruns.py
hermes/datamodel/alembic/versions/ce906ec117f1_rename_seismicevent_to_eventforecast.py
hermes/datamodel/alembic/versions/eecc136ab320_add_indexes_for_deletion_cascades.py
hermes/datamodel/alembic/versions_utils/e54a6a77d721_create_utils_branch.py
hermes/flows/__init__.py
hermes/flows/forecast_runner.py
hermes/flows/forecast_tasks.py
hermes/flows/forecastseries_deployment.py
hermes/flows/forecastseries_scheduler.py
hermes/flows/modelrun_handler.py
hermes/flows/tests/__init__.py
hermes/flows/tests/conftest.py
hermes/flows/tests/test_forecast_runner.py
hermes/flows/tests/test_forecastseries_scheduler.py
hermes/flows/tests/test_modelrun_handler.py
hermes/io/__init__.py
hermes/io/datasource.py
hermes/io/hydraulics.py
hermes/io/injectionplans.py
hermes/io/seismicity.py
hermes/io/serialize.py
rt_hermes-1.1.0.dist-info/licenses/LICENSE
rt_hermes-1.1.0.dist-info/METADATA
rt_hermes-1.1.0.dist-info/WHEEL
rt_hermes-1.1.0.dist-info/entry_points.txt
rt_hermes-1.1.0.dist-info/top_level.txt
rt_hermes-1.1.0.dist-info/RECORD
