Metadata-Version: 2.4
Name: rt-hermes
Version: 1.1.0
Summary: RealTime Hub for Earthquake foRecasts ManagEment and Scheduling 
Author: Laura Sarson, Nicolas Schmid
License:                     GNU AFFERO GENERAL PUBLIC LICENSE
Project-URL: Documentation, https://github.com/swiss-seismological-service/rt-hermes
Project-URL: Repository, https://github.com/swiss-seismological-service/rt-hermes
Project-URL: Issues, https://github.com/swiss-seismological-service/rt-hermes/issues
Classifier: Environment :: Console
Classifier: Intended Audience :: Science/Research
Classifier: Intended Audience :: Education
Classifier: Operating System :: OS Independent
Classifier: License :: OSI Approved :: GNU Affero General Public License v3
Classifier: Programming Language :: Python :: 3
Classifier: Programming Language :: Python :: 3.12
Classifier: Programming Language :: Python :: 3.13
Classifier: Topic :: Scientific/Engineering
Classifier: Topic :: Scientific/Engineering :: Physics
Requires-Python: <3.14,>=3.12
License-File: LICENSE
Requires-Dist: alembic-utils
Requires-Dist: alembic
Requires-Dist: geoalchemy2
Requires-Dist: hermes-model
Requires-Dist: hydws-client>=1.3.1
Requires-Dist: pandas
Requires-Dist: prefect<3.6.0
Requires-Dist: psycopg2
Requires-Dist: pydantic-settings
Requires-Dist: pydantic
Requires-Dist: python-dotenv
Requires-Dist: requests
Requires-Dist: seismostats
Requires-Dist: shapely
Requires-Dist: sqlalchemy
Requires-Dist: typer
Provides-Extra: dev
Requires-Dist: build; extra == "dev"
Requires-Dist: flake8; extra == "dev"
Requires-Dist: isort; extra == "dev"
Requires-Dist: pyarrow; extra == "dev"
Requires-Dist: pytest-asyncio; extra == "dev"
Requires-Dist: pytest-cov; extra == "dev"
Requires-Dist: pytest; extra == "dev"
Requires-Dist: setuptools-scm; extra == "dev"
Requires-Dist: tox; extra == "dev"
Requires-Dist: twine; extra == "dev"
Dynamic: license-file
